agent.py
bluesky_client.py
reddit_client.py
social_search_agent-0.1.2.dist-info/licenses/LICENSE
social_search_agent-0.1.2.dist-info/METADATA
social_search_agent-0.1.2.dist-info/WHEEL
social_search_agent-0.1.2.dist-info/entry_points.txt
social_search_agent-0.1.2.dist-info/top_level.txt
social_search_agent-0.1.2.dist-info/RECORD
