Metadata-Version: 2.4
Name: social-search-agent
Version: 0.1.2
Summary: Research agent using GPT-5.2 to search Reddit and Bluesky
Author: Social Search
License: MIT
Project-URL: Homepage, https://github.com/TanushV/social-search
Project-URL: Repository, https://github.com/TanushV/social-search
Keywords: reddit,bluesky,research,agent,openai,gpt
Classifier: Development Status :: 3 - Alpha
Classifier: Intended Audience :: Developers
Classifier: License :: OSI Approved :: MIT License
Classifier: Programming Language :: Python :: 3
Classifier: Programming Language :: Python :: 3.10
Classifier: Programming Language :: Python :: 3.11
Classifier: Programming Language :: Python :: 3.12
Requires-Python: >=3.10
License-File: LICENSE
Requires-Dist: praw>=7.7.0
Requires-Dist: python-dotenv>=1.0.0
Requires-Dist: atproto>=0.0.50
Requires-Dist: requests>=2.31.0
Requires-Dist: openai>=1.0.0
Requires-Dist: rich>=13.0.0
Dynamic: license-file
